<annotation>
  <folder>./resized_all_raw_celebrities/</folder>
  <filename>0379af29e9297e59836c2d6588b8a93f.jpg</filename>
  <path>./resized_all_raw_celebrities/0379af29e9297e59836c2d6588b8a93f.jpg</path>
  <source>
    <database>Unknown</database>
  </source>
  <size>
    <width>800</width>
    <height>600</height>
    <depth>3</depth>
  </size>
  <segmented>0</segmented>
  <object>
    <name>ShahrukhKhan</name>
    <pose>Unspecified</pose>
    <truncated>0</truncated>
    <difficult>0</difficult>
    <bndbox>
      <xmin>158</xmin>
      <ymin>105</ymin>
      <xmax>581</xmax>
      <ymax>528</ymax>
    </bndbox>
  </object>
</annotation>
