<annotation>
  <folder>./resized_all_raw_celebrities/</folder>
  <filename>07e798e431e57ffe40819f211d24cc69.jpg</filename>
  <path>./resized_all_raw_celebrities/07e798e431e57ffe40819f211d24cc69.jpg</path>
  <source>
    <database>Unknown</database>
  </source>
  <size>
    <width>521</width>
    <height>800</height>
    <depth>3</depth>
  </size>
  <segmented>0</segmented>
  <object>
    <name>SalmanKhan</name>
    <pose>Unspecified</pose>
    <truncated>0</truncated>
    <difficult>0</difficult>
    <bndbox>
      <xmin>295</xmin>
      <ymin>110</ymin>
      <xmax>465</xmax>
      <ymax>280</ymax>
    </bndbox>
  </object>
</annotation>
