<annotation>
  <folder>./resized_all_raw_celebrities/</folder>
  <filename>293caaad78182b36b22e2a7942eb5567.jpg</filename>
  <path>./resized_all_raw_celebrities/293caaad78182b36b22e2a7942eb5567.jpg</path>
  <source>
    <database>Unknown</database>
  </source>
  <size>
    <width>533</width>
    <height>800</height>
    <depth>3</depth>
  </size>
  <segmented>0</segmented>
  <object>
    <name>KatrinaKaif</name>
    <pose>Unspecified</pose>
    <truncated>0</truncated>
    <difficult>0</difficult>
    <bndbox>
      <xmin>75</xmin>
      <ymin>107</ymin>
      <xmax>279</xmax>
      <ymax>311</ymax>
    </bndbox>
  </object>
</annotation>
