<annotation>
  <folder>./resized_all_raw_celebrities/</folder>
  <filename>4c9aee58b5eccad794ddeed287183339.jpg</filename>
  <path>./resized_all_raw_celebrities/4c9aee58b5eccad794ddeed287183339.jpg</path>
  <source>
    <database>Unknown</database>
  </source>
  <size>
    <width>800</width>
    <height>600</height>
    <depth>3</depth>
  </size>
  <segmented>0</segmented>
  <object>
    <name>AmitabhBachchan</name>
    <pose>Unspecified</pose>
    <truncated>0</truncated>
    <difficult>0</difficult>
    <bndbox>
      <xmin>388</xmin>
      <ymin>174</ymin>
      <xmax>591</xmax>
      <ymax>378</ymax>
    </bndbox>
  </object>
</annotation>
