<annotation>
  <folder>./resized_all_raw_celebrities/</folder>
  <filename>94895d6c94ae2b8bfe9ac38a3e8b5f07.jpg</filename>
  <path>./resized_all_raw_celebrities/94895d6c94ae2b8bfe9ac38a3e8b5f07.jpg</path>
  <source>
    <database>Unknown</database>
  </source>
  <size>
    <width>800</width>
    <height>600</height>
    <depth>3</depth>
  </size>
  <segmented>0</segmented>
  <object>
    <name>ShahrukhKhan</name>
    <pose>Unspecified</pose>
    <truncated>0</truncated>
    <difficult>0</difficult>
    <bndbox>
      <xmin>236</xmin>
      <ymin>80</ymin>
      <xmax>529</xmax>
      <ymax>374</ymax>
    </bndbox>
  </object>
</annotation>
