<annotation>
  <folder>./resized_all_raw_celebrities/</folder>
  <filename>954c6cfa98609f142198a4c19a71c83a.jpg</filename>
  <path>./resized_all_raw_celebrities/954c6cfa98609f142198a4c19a71c83a.jpg</path>
  <source>
    <database>Unknown</database>
  </source>
  <size>
    <width>800</width>
    <height>600</height>
    <depth>3</depth>
  </size>
  <segmented>0</segmented>
  <object>
    <name>DeepikaPadukone</name>
    <pose>Unspecified</pose>
    <truncated>0</truncated>
    <difficult>0</difficult>
    <bndbox>
      <xmin>304</xmin>
      <ymin>138</ymin>
      <xmax>549</xmax>
      <ymax>382</ymax>
    </bndbox>
  </object>
</annotation>
