<annotation>
  <folder>./resized_all_raw_celebrities/</folder>
  <filename>aa4e3d8c7d5cc18e9a78d79b41edf3ff.jpg</filename>
  <path>./resized_all_raw_celebrities/aa4e3d8c7d5cc18e9a78d79b41edf3ff.jpg</path>
  <source>
    <database>Unknown</database>
  </source>
  <size>
    <width>675</width>
    <height>800</height>
    <depth>3</depth>
  </size>
  <segmented>0</segmented>
  <object>
    <name>DeepikaPadukone</name>
    <pose>Unspecified</pose>
    <truncated>0</truncated>
    <difficult>0</difficult>
    <bndbox>
      <xmin>212</xmin>
      <ymin>135</ymin>
      <xmax>456</xmax>
      <ymax>379</ymax>
    </bndbox>
  </object>
</annotation>
