<annotation>
  <folder>./resized_all_raw_celebrities/</folder>
  <filename>d10e3bd8e5af6f44a4f55b04aa71154f.jpg</filename>
  <path>./resized_all_raw_celebrities/d10e3bd8e5af6f44a4f55b04aa71154f.jpg</path>
  <source>
    <database>Unknown</database>
  </source>
  <size>
    <width>591</width>
    <height>800</height>
    <depth>3</depth>
  </size>
  <segmented>0</segmented>
  <object>
    <name>SonamKapoor</name>
    <pose>Unspecified</pose>
    <truncated>0</truncated>
    <difficult>0</difficult>
    <bndbox>
      <xmin>156</xmin>
      <ymin>135</ymin>
      <xmax>400</xmax>
      <ymax>379</ymax>
    </bndbox>
  </object>
</annotation>
