<annotation>
  <folder>./resized_all_raw_celebrities/</folder>
  <filename>efa8a2eae90fca4adb59d531b5d141d4.jpg</filename>
  <path>./resized_all_raw_celebrities/efa8a2eae90fca4adb59d531b5d141d4.jpg</path>
  <source>
    <database>Unknown</database>
  </source>
  <size>
    <width>800</width>
    <height>500</height>
    <depth>3</depth>
  </size>
  <segmented>0</segmented>
  <object>
    <name>AkshayKumar</name>
    <pose>Unspecified</pose>
    <truncated>0</truncated>
    <difficult>0</difficult>
    <bndbox>
      <xmin>243</xmin>
      <ymin>148</ymin>
      <xmax>447</xmax>
      <ymax>352</ymax>
    </bndbox>
  </object>
</annotation>
